odoo/addons/hr_shift/README.rst
odoo/addons/hr_shift/__init__.py
odoo/addons/hr_shift/__manifest__.py
odoo/addons/hr_shift/demo/demo.xml
odoo/addons/hr_shift/i18n/es.po
odoo/addons/hr_shift/i18n/hr_shift.pot
odoo/addons/hr_shift/i18n/it.po
odoo/addons/hr_shift/models/__init__.py
odoo/addons/hr_shift/models/hr_employee.py
odoo/addons/hr_shift/models/res_company.py
odoo/addons/hr_shift/models/res_config_settings.py
odoo/addons/hr_shift/models/resource_calendar.py
odoo/addons/hr_shift/models/shift_planning.py
odoo/addons/hr_shift/models/shift_template.py
odoo/addons/hr_shift/readme/CONFIGURE.md
odoo/addons/hr_shift/readme/CONTRIBUTORS.md
odoo/addons/hr_shift/readme/CREDITS.md
odoo/addons/hr_shift/readme/DESCRIPTION.md
odoo/addons/hr_shift/readme/ROADMAP.md
odoo/addons/hr_shift/readme/USAGE.md
odoo/addons/hr_shift/security/hr_shift_security.xml
odoo/addons/hr_shift/security/ir.model.access.csv
odoo/addons/hr_shift/static/description/assignment_details_dragging.gif
odoo/addons/hr_shift/static/description/assignment_dragging.gif
odoo/addons/hr_shift/static/description/icon.png
odoo/addons/hr_shift/static/description/icon.svg
odoo/addons/hr_shift/static/description/index.html
odoo/addons/hr_shift/static/description/planning_card.png
odoo/addons/hr_shift/static/description/reviewed_checkbox.png
odoo/addons/hr_shift/static/description/week_days_colors.png
odoo/addons/hr_shift/static/src/js/field_utils.js
odoo/addons/hr_shift/static/src/js/generate_planning.js
odoo/addons/hr_shift/static/src/scss/shift.scss
odoo/addons/hr_shift/static/src/xml/generate_planning_views.xml
odoo/addons/hr_shift/views/assets.xml
odoo/addons/hr_shift/views/hr_employee_views.xml
odoo/addons/hr_shift/views/res_config_settings_views.xml
odoo/addons/hr_shift/views/shift_planning_views.xml
odoo/addons/hr_shift/views/shift_template_views.xml
odoo/addons/hr_shift/wizards/__init__.py
odoo/addons/hr_shift/wizards/shift_planning_wizard.py
odoo/addons/hr_shift/wizards/shift_planning_wizard_views.xml
odoo14_addon_hr_shift-14.0.1.0.1.dev3.dist-info/METADATA
odoo14_addon_hr_shift-14.0.1.0.1.dev3.dist-info/WHEEL
odoo14_addon_hr_shift-14.0.1.0.1.dev3.dist-info/top_level.txt
odoo14_addon_hr_shift-14.0.1.0.1.dev3.dist-info/RECORD
